cli.py
rashdf/__init__.py
rashdf/base.py
rashdf/geom.py
rashdf/plan.py
rashdf/utils.py
rashdf-0.10.0.dist-info/licenses/LICENSE
rashdf-0.10.0.dist-info/METADATA
rashdf-0.10.0.dist-info/WHEEL
rashdf-0.10.0.dist-info/entry_points.txt
rashdf-0.10.0.dist-info/top_level.txt
rashdf-0.10.0.dist-info/RECORD
