Metadata-Version: 2.4
Name: rashdf
Version: 0.10.0
Summary: Read data from HEC-RAS HDF files.
Project-URL: repository, https://github.com/fema-ffrd/rashdf
Classifier: Development Status :: 4 - Beta
Classifier: Intended Audience :: Developers
Classifier: License :: OSI Approved :: MIT License
Classifier: Programming Language :: Python :: 3
Classifier: Programming Language :: Python :: 3.10
Classifier: Programming Language :: Python :: 3.11
Classifier: Programming Language :: Python :: 3.12
Classifier: Programming Language :: Python :: 3.13
License-File: LICENSE
Requires-Dist: h5py
Requires-Dist: geopandas<2.0,>=1.0
Requires-Dist: pyarrow
Requires-Dist: xarray<=2025.4.0
Provides-Extra: dev
Requires-Dist: pre-commit; extra == "dev"
Requires-Dist: ruff; extra == "dev"
Requires-Dist: pytest; extra == "dev"
Requires-Dist: pytest-cov; extra == "dev"
Requires-Dist: kerchunk; extra == "dev"
Requires-Dist: zarr==2.18.2; extra == "dev"
Requires-Dist: dask; extra == "dev"
Requires-Dist: fsspec; extra == "dev"
Requires-Dist: s3fs; extra == "dev"
Requires-Dist: fiona==1.9.6; extra == "dev"
Requires-Dist: numcodecs<0.16; extra == "dev"
Provides-Extra: docs
Requires-Dist: sphinx; extra == "docs"
Requires-Dist: numpydoc; extra == "docs"
Requires-Dist: sphinx_rtd_theme; extra == "docs"
Dynamic: license-file
